guide_gitlab/__about__.py
guide_gitlab/__init__.py
guide_gitlab/exceptions.py
guide_gitlab/gitlab.py
guide_gitlab-0.0.21.dist-info/METADATA
guide_gitlab-0.0.21.dist-info/RECORD
guide_gitlab-0.0.21.dist-info/WHEEL
guide_gitlab-0.0.21.dist-info/top_level.txt
